sentinella_libvirt-0.1.1-nspkg.pth
sentinella_libvirt-0.1.1.dist-info/METADATA
sentinella_libvirt-0.1.1.dist-info/WHEEL
sentinella_libvirt-0.1.1.dist-info/DESCRIPTION.rst
sentinella_libvirt-0.1.1.dist-info/metadata.json
sentinella_libvirt-0.1.1.dist-info/RECORD
sentinella_libvirt-0.1.1.dist-info/namespace_packages.txt
sentinella_libvirt-0.1.1.dist-info/top_level.txt
sentinella/libvirt/__init__.py
sentinella/libvirt/libvirt2/__init__.py
sentinella/libvirt/libvirt2/libvirt.py
sentinella/sentinella_libvirt/__init__.py
sentinella/sentinella_libvirt/sentinella_libvirt/libvirtmon.py
sentinella/sentinella_libvirt/sentinella_libvirt/__init__.py
sentinella/sentinella_libvirt/sentinella_libvirt/sentinella_libvirt.py
